qywechat/__init__.py
qywechat/common.py
qywechat/parsers.py
qywechat/base/__init__.py
qywechat/base/_base.py
qywechat/message/__init__.py
qywechat/message/_message.py
qywechat/oa/__init__.py
qywechat/oa/_oa.py
qywechat/robot/__init__.py
qywechat/robot/_robot.py
qywechat/tests/__init__.py
qywechat/tests/base/__init__.py
qywechat/tests/base/test_base.py
snowland_qyweixin-0.0.4.post1.dist-info/LICENSE
snowland_qyweixin-0.0.4.post1.dist-info/METADATA
snowland_qyweixin-0.0.4.post1.dist-info/WHEEL
snowland_qyweixin-0.0.4.post1.dist-info/top_level.txt
snowland_qyweixin-0.0.4.post1.dist-info/RECORD
