Metadata-Version: 2.1
Name: snowland-qyweixin
Version: 0.0.4.post1
Summary: toolkit for qyweixin. 企业微信开发SDK。
Home-page: https://gitee.com/snowlandltd/snowland-qyweixin-python
Author: A.Star
Author-email: astar@snowland.ltd
Maintainer: A.Star
Maintainer-email: astar@snowland.ltd
License: Apache v2.0
Platform: all
Classifier: Operating System :: OS Independent
Classifier: Intended Audience :: Developers
Classifier: Programming Language :: Python
Classifier: Programming Language :: Python :: Implementation
Classifier: Programming Language :: Python :: 3
Classifier: Programming Language :: Python :: 3.6
Classifier: Programming Language :: Python :: 3.7
Classifier: Programming Language :: Python :: 3.8
Classifier: Programming Language :: Python :: 3.9
Classifier: Topic :: Software Development :: Libraries
License-File: LICENSE
Requires-Dist: astartool (>=0.0.7)
Requires-Dist: snowland-authsdk (>=0.0.1)
Requires-Dist: snowland-smx
Requires-Dist: requests
